{
  "indexes": [
    {
      "collectionGroup": "watson_exports",
      "queryScope": "COLLECTION",
      "fields": [
        { "fieldPath": "status", "order": "ASCENDING" },
        { "fieldPath": "confirmedAt", "order": "DESCENDING" }
      ]
    },
    {
      "collectionGroup": "watson_exports",
      "queryScope": "COLLECTION",
      "fields": [
        { "fieldPath": "status", "order": "ASCENDING" },
        { "fieldPath": "exportedAt", "order": "DESCENDING" }
      ]
    },
    {
      "collectionGroup": "watson_exports",
      "queryScope": "COLLECTION",
      "fields": [
        { "fieldPath": "companyId", "order": "ASCENDING" },
        { "fieldPath": "confirmedAt", "order": "DESCENDING" }
      ]
    },
    {
      "collectionGroup": "watson_exports",
      "queryScope": "COLLECTION",
      "fields": [
        { "fieldPath": "companyId", "order": "ASCENDING" },
        { "fieldPath": "exportedAt", "order": "DESCENDING" }
      ]
    },
    {
      "collectionGroup": "watson_exports",
      "queryScope": "COLLECTION",
      "fields": [
        { "fieldPath": "companyId", "order": "ASCENDING" },
        { "fieldPath": "status", "order": "ASCENDING" },
        { "fieldPath": "confirmedAt", "order": "DESCENDING" }
      ]
    },
    {
      "collectionGroup": "watson_exports",
      "queryScope": "COLLECTION",
      "fields": [
        { "fieldPath": "companyId", "order": "ASCENDING" },
        { "fieldPath": "status", "order": "ASCENDING" },
        { "fieldPath": "exportedAt", "order": "DESCENDING" }
      ]
    },
    {
      "collectionGroup": "watson_exports",
      "queryScope": "COLLECTION",
      "fields": [
        { "fieldPath": "supplierCode", "order": "ASCENDING" },
        { "fieldPath": "confirmedAt", "order": "DESCENDING" }
      ]
    },
    {
      "collectionGroup": "watson_exports",
      "queryScope": "COLLECTION",
      "fields": [
        { "fieldPath": "supplierCode", "order": "ASCENDING" },
        { "fieldPath": "exportedAt", "order": "DESCENDING" }
      ]
    },
    {
      "collectionGroup": "watson_exports",
      "queryScope": "COLLECTION",
      "fields": [
        { "fieldPath": "invoiceUploadId", "order": "ASCENDING" },
        { "fieldPath": "exportedAt", "order": "DESCENDING" }
      ]
    },
    {
      "collectionGroup": "watson_exports",
      "queryScope": "COLLECTION",
      "fields": [
        { "fieldPath": "invoiceUploadId", "order": "ASCENDING" },
        { "fieldPath": "confirmedAt", "order": "DESCENDING" }
      ]
    },
    {
      "collectionGroup": "shopStockReceives",
      "queryScope": "COLLECTION",
      "fields": [
        { "fieldPath": "receivedBy", "order": "ASCENDING" },
        { "fieldPath": "createdAt", "order": "DESCENDING" }
      ]
    },
    {
      "collectionGroup": "shopStockReceives",
      "queryScope": "COLLECTION",
      "fields": [
        { "fieldPath": "companyId", "order": "ASCENDING" },
        { "fieldPath": "branchId", "order": "ASCENDING" },
        { "fieldPath": "receivedAt", "order": "DESCENDING" }
      ]
    }
  ],
  "fieldOverrides": []
}
